segmentation_robustness_framework/__init__.py
segmentation_robustness_framework/__version__.py
segmentation_robustness_framework/adapters/__init__.py
segmentation_robustness_framework/adapters/base_protocol.py
segmentation_robustness_framework/adapters/custom_adapter.py
segmentation_robustness_framework/adapters/huggingface_adapter.py
segmentation_robustness_framework/adapters/registry.py
segmentation_robustness_framework/adapters/smp_adapter.py
segmentation_robustness_framework/adapters/torchvision_adapter.py
segmentation_robustness_framework/attacks/__init__.py
segmentation_robustness_framework/attacks/attack.py
segmentation_robustness_framework/attacks/fgsm.py
segmentation_robustness_framework/attacks/pgd.py
segmentation_robustness_framework/attacks/registry.py
segmentation_robustness_framework/attacks/rfgsm.py
segmentation_robustness_framework/attacks/tpgd.py
segmentation_robustness_framework/cli/__init__.py
segmentation_robustness_framework/cli/list_attacks.py
segmentation_robustness_framework/cli/list_components.py
segmentation_robustness_framework/cli/list_datasets.py
segmentation_robustness_framework/cli/list_metrics.py
segmentation_robustness_framework/cli/main.py
segmentation_robustness_framework/cli/run_config.py
segmentation_robustness_framework/cli/run_tests.py
segmentation_robustness_framework/datasets/__init__.py
segmentation_robustness_framework/datasets/ade20k.py
segmentation_robustness_framework/datasets/cityscapes.py
segmentation_robustness_framework/datasets/registry.py
segmentation_robustness_framework/datasets/stanford_background.py
segmentation_robustness_framework/datasets/voc.py
segmentation_robustness_framework/loaders/__init__.py
segmentation_robustness_framework/loaders/attack_loader.py
segmentation_robustness_framework/loaders/dataset_loader.py
segmentation_robustness_framework/loaders/models/__init__.py
segmentation_robustness_framework/loaders/models/base.py
segmentation_robustness_framework/loaders/models/custom_loader.py
segmentation_robustness_framework-0.3.1.dist-info/LICENSE
segmentation_robustness_framework-0.3.1.dist-info/METADATA
segmentation_robustness_framework-0.3.1.dist-info/WHEEL
segmentation_robustness_framework-0.3.1.dist-info/entry_points.txt
segmentation_robustness_framework-0.3.1.dist-info/RECORD
