Metadata-Version: 2.3
Name: segmentation-robustness-framework
Version: 0.3.1
Summary: Segmentation Robustness Framework - a powerful toolkit for evaluating the robustness of semantic segmentation models against adversarial attacks.
License: MIT
Author: Egor Vorobyev
Author-email: voro6yov.egor@gmail.com
Requires-Python: >=3.12,<4.0
Classifier: License :: OSI Approved :: MIT License
Classifier: Programming Language :: Python :: 3
Classifier: Programming Language :: Python :: 3.12
Classifier: Programming Language :: Python :: 3.13
Provides-Extra: full
Provides-Extra: smp
Provides-Extra: transformers
Requires-Dist: matplotlib (>=3.10.0,<4.0.0)
Requires-Dist: numpy (>=2.3.0,<3.0.0)
Requires-Dist: pandas (>=2.3.1,<3.0.0)
Requires-Dist: pyyaml (>=6.0.2,<7.0.0)
Requires-Dist: segmentation-models-pytorch (>=0.5.0,<0.6.0) ; extra == "smp" or extra == "full"
Requires-Dist: torch (==2.6.0)
Requires-Dist: torchvision (==0.21.0)
Requires-Dist: tqdm (>=4.67.1,<5.0.0)
Requires-Dist: transformers (>=4.53.1,<5.0.0) ; extra == "transformers" or extra == "full"
Requires-Dist: types-pyyaml (>=6.0.12.20240917,<7.0.0.0)
